{
  "type": "FeatureCollection",
  "features": [
    {
      "type": "Feature",
      "properties": {
        "name": "Fahrradmarkt",
        "description": "<strong>Kölner Fahrradmarkt</strong> <br>Art: Fahrradmarkt  <br> Ort: Neptunplatz <br>Barrierefrei: Ja <br>Outdoor/Indoor: Outdoor <br>Haltestelle: Körnerstraße mit den Linien 3, 4 <br>Eintritt: 0 Euro <br><a href='http://www.fahrradmarkt-koeln.de/termine/' target='_blank'>www.fahrradmarkt-koeln.de</a>",
        "Ort": "Neptunplatz",
        "Barrierefrei": "Ja",
        "Outdoor/Indoor": "Outdoor",
        "Wie komme ich hin?": "Haltestelle Körnerstraße mit den Linien 3,4",
        "Wann": "25.01.2020, 15.02.2020, 21.03.2020",
        "Eintritt": "0 Euro",
        "Link": "http://www.fahrradmarkt-koeln.de/termine/",
        "Art": "Fahrradmarkt"
      },
      "geometry": {
        "type": "Point",
        "coordinates": [
          6.919519901275635,
          50.94758574982511
        ]
      }
    },
    {
      "type": "Feature",
      "properties": {
        "name": "Fahrradmarkt",
        "description": "<strong>Kölner Fahrradmarkt</strong> <br>Art: Fahrradmarkt  <br> Ort: Neptunplatz <br>Barrierefrei: Ja <br>Outdoor/Indoor: Outdoor <br>Haltestelle: Kalk Post mit den Linien 1, 9<br>Eintritt: 0 Euro <br><a href='http://www.fahrradmarkt-koeln.de/termine/' target='_blank'>www.fahrradmarkt-koeln.de</a>",
        "Ort": "Bürgerpark Kalk",
        "Barrierefrei": "Ja",
        "Outdoor/Indoor": "Outdoor",
        "Wie komme ich hin?": "Haltestelle Kalk Post mit den Linien 1,9",
        "Wann": "28.03.2020, 25.04.2020, 23.05.2020, 27.06.2020",
        "Eintritt": "0 Euro",
        "Link": "http://www.fahrradmarkt-koeln.de/termine/",
        "Art": "Fahrradmarkt"
      },
      "geometry": {
        "type": "Point",
        "coordinates": [
          6.99555516242981,
          50.9403592827131
        ]
      }
    }
  ]
}