{
  "type": "FeatureCollection",
  "features": [
    {
      "type": "Feature",
      "properties": {
        "name": "Fahrradmarkt",
        "description": "<strong>Kölner Fahrradmarkt</strong> <br>Art: Fahrradmarkt  <br> Ort: Neptunplatz <br>Barrierefrei: Ja <br>Outdoor/Indoor: Outdoor <br>Haltestelle: Körnerstraße mit den Linien 3, 4 <br>Eintritt: 0 Euro <br><a href='http://www.fahrradmarkt-koeln.de/termine/' target='_blank'>www.fahrradmarkt-koeln.de</a>",
        "Ort": "Neptunplatz",
        "Barrierefrei": "Ja",
        "Outdoor/Indoor": "Outdoor",
        "Wie komme ich hin?": "Haltestelle Körnerstraße mit den Linien 3,4",
        "Wann": "25.01.2020, 15.02.2020, 21.03.2020",
        "Eintritt": "0 Euro",
        "Link": "http://www.fahrradmarkt-koeln.de/termine/",
        "Art": "Fahrradmarkt"
      },
      "geometry": {
        "type": "Point",
        "coordinates": [
          6.919519901275635,
          50.94758574982511
        ]
      }
    },
    {
      "type": "Feature",
      "properties": {
        "name": "Fahrradmarkt",
        "description": "<strong>Kölner Fahrradmarkt</strong> <br>Art: Fahrradmarkt  <br> Ort: Bürgerpark, Barcelona-Allee/ Rückseite Kalkarkaden <br>Barrierefrei: Ja <br>Outdoor/Indoor: Outdoor <br>Haltestelle: Kalk Post mit den Linien 1, 9<br>Eintritt: 0 Euro <br><a href='http://www.fahrradmarkt-koeln.de/termine/' target='_blank'>www.fahrradmarkt-koeln.de</a>",
        "Ort": "Bürgerpark Kalk",
        "Barrierefrei": "Ja",
        "Outdoor/Indoor": "Outdoor",
        "Wie komme ich hin?": "Haltestelle Kalk Post mit den Linien 1,9",
        "Wann": "28.03.2020, 25.04.2020, 23.05.2020, 27.06.2020",
        "Eintritt": "0 Euro",
        "Link": "http://www.fahrradmarkt-koeln.de/termine/",
        "Art": "Fahrradmarkt"
      },
      "geometry": {
        "type": "Point",
        "coordinates": [
          6.99555516242981,
          50.9403592827131
        ]
      }
    },
    {
      "type": "Feature",
      "properties": {
        "name": "Fahrradmarkt Nippes",
        "description": "<strong>Fahrradmarkt Nippes</strong> <br>Art: Fahrradmarkt  <br> Ort: Vorplatz Agneskirche/Neusser Platz <br>Barrierefrei: Ja <br>Outdoor/Indoor: Outdoor <br>Haltestelle: Ebertplatz: 12, 15, 16, 18, 127, 140<br>Eintritt: 0 Euro <br><a href='https://www.fahrradmarkt-koeln.de/termine/' target='_blank'>https://www.fahrradmarkt-koeln.de/termine/</a>",
        "Ort": "Vorplatz Agneskirche/Neusser Platz",
        "Barrierefrei": "Ja",
        "Outdoor/Indoor": "Outdoor",
        "Wie komme ich hin?": "Haltestelle Ebertplatz: 12, 15, 16, 18, 127, 140",
        "Wann": "04.04.20, 02.05.20, 06.06.20, 8 bis 16 Uhr",
        "Eintritt": "0 Euro",
        "Link": "https://www.fahrradmarkt-koeln.de/termine/",
        "Art": "Fahrradmarkt"
      },
      "geometry": {
        "type": "Point",
        "coordinates": [
          6.958016,
          50.954933
        ]
      }
    },
    {
      "type": "Feature",
      "properties": {
        "name": "Fahrradmarkt Innenstadt",
        "description": "<strong>Fahrradmarkt Innenstadt</strong> <br>Art: Fahrradmarkt  <br> Ort: Friesenplatz <br>Barrierefrei: Ja <br>Outdoor/Indoor: Outdoor <br>Haltestelle: Friesenplatz: 3, 4, 5, 12, 15, 172, 173<br>Eintritt: 0 Euro <br><a href='https://www.fahrradmarkt-koeln.de/termine/' target='_blank'>https://www.fahrradmarkt-koeln.de/termine/</a>",
        "Ort": "Friesenplatz",
        "Barrierefrei": "Ja",
        "Outdoor/Indoor": "Outdoor",
        "Wie komme ich hin?": "Haltestelle Friesenplatz: 3, 4, 5, 12, 15, 172, 173",
        "Wann": "14.03.20, 11.04.20, 09.05.20, 13.06.20, 8 bis 16 Uhr",
        "Eintritt": "0 Euro",
        "Link": "https://www.fahrradmarkt-koeln.de/termine/",
        "Art": "Fahrradmarkt"
      },
      "geometry": {
        "type": "Point",
        "coordinates": [
          6.940107,
          50.940927
        ]
      }
    },
    {
      "type": "Feature",
      "properties": {
        "name": "Fahrradmarkt Südstadt",
        "description": "<strong>Fahrradmarkt Südstadt</strong> <br>Art: Fahrradmarkt  <br> Ort: Severinsvorplatz <br>Barrierefrei: Ja <br>Outdoor/Indoor: Outdoor <br>Haltestelle: Kartäuserhof: 16, 17<br>Eintritt: 0 Euro <br><a href='https://www.fahrradmarkt-koeln.de/termine/' target='_blank'>https://www.fahrradmarkt-koeln.de/termine/</a>",
        "Ort": "Severinsvorplatz",
        "Barrierefrei": "Ja",
        "Outdoor/Indoor": "Outdoor",
        "Wie komme ich hin?": "Haltestelle Kartäuserhof: 16, 17",
        "Wann": "30.05.20, 8 bis 16 Uhr",
        "Eintritt": "0 Euro",
        "Link": "https://www.fahrradmarkt-koeln.de/termine/",
        "Art": "Fahrradmarkt"
      },
      "geometry": {
        "type": "Point",
        "coordinates": [
          6.959545,
          50.923345
        ]
      }
    } 
  ]
}
